{
  "generated_at": "2026-03-13T02:42:38.141028+08:00",
  "total_titles_processed": 430,
  "failed_sources": [],
  "trends": [
    {
      "keyword_group": "美国 大陆 日本 俄罗斯 台湾",
      "match_count": 52,
      "titles": [
        {
          "title": "美国防部被曝龙虾门",
          "url": "https://search.bilibili.com/all?keyword=%E7%BE%8E%E5%9B%BD%E9%98%B2%E9%83%A8%E8%A2%AB%E6%9B%9D%E9%BE%99%E8%99%BE%E9%97%A8",
          "source": "bilibili 热搜",
          "ranks": [
            1
          ],
          "is_new": false,
          "appearance_count": 3,
          "time_info": "[00时52分 ~ 02时42分]"
        },
        {
          "title": "美国贸易代表：将对16个贸易伙伴发起301调查",
          "url": "https://m.thepaper.cn/newsDetail_forward_32752869",
          "source": "澎湃新闻",
          "ranks": [
            2
          ],
          "is_new": false,
          "appearance_count": 3,
          "time_info": "[00时52分 ~ 02时42分]"
        },
        {
          "title": "专访｜达巍：中国不会也无意填补美国留下的“真空”",
          "url": "https://m.thepaper.cn/newsDetail_forward_32746254",
          "source": "澎湃新闻",
          "ranks": [
            3,
            4
          ],
          "is_new": false,
          "appearance_count": 3,
          "time_info": "[00时52分 ~ 02时42分]"
        },
        {
          "title": "日本官员承认出轨，高市早苗让他“用工作弥补”",
          "url": "https://news.ifeng.com/c/8rR8BDRz10z",
          "source": "凤凰网",
          "ranks": [
            5
          ],
          "is_new": false,
          "appearance_count": 3,
          "time_info": "[00时52分 ~ 02时42分]"
        },
        {
          "title": "美国密歇根州西布卢姆菲尔德（West Bloomfield）一座犹太教堂报告“枪击事件”。",
          "url": "https://flash.jin10.com/detail/20260313013009560800",
          "source": "金十数据",
          "ranks": [
            2,
            25
          ],
          "is_new": false,
          "appearance_count": 2,
          "time_info": "[01时43分 ~ 02时42分]"
        },
        {
          "title": "美国各大交易所的CEO们呼吁审查预测市场“简易上市”制度",
          "url": "https://wallstreetcn.com/livenews/3069084",
          "source": "华尔街见闻-快讯",
          "ranks": [
            3,
            18
          ],
          "is_new": false,
          "appearance_count": 2,
          "time_info": "[01时43分 ~ 02时42分]"
        },
        {
          "title": "美国参议院批准跨党派提出的住房经适性立法草案，按89-10票支持扩大全美住房供应。 草案中包含限制华尔街染指住房市场的条款。",
          "url": "https://wallstreetcn.com/livenews/3069061",
          "source": "华尔街见闻-快讯",
          "ranks": [
            4,
            22
          ],
          "is_new": false,
          "appearance_count": 2,
          "time_info": "[00时52分 ~ 01时43分]"
        },
        {
          "title": "乌克兰总统泽连斯基：发展两国间的能源网络至关重要，这不仅有助于乌克兰应对俄罗斯持续攻击能源基础设施造成的能源短缺，还能在我们电力盈余并可出口电力时为罗马尼亚提供支持。因此，能源领域的合作也是我们讨论的重点议题。",
          "url": "https://flash.jin10.com/detail/20260313012833651800",
          "source": "金十数据",
          "ranks": [
            5,
            28
          ],
          "is_new": false,
          "appearance_count": 2,
          "time_info": "[01时43分 ~ 02时42分]"
        },
        {
          "title": "美国抵押贷款利率创最近11个月最大升幅，伊朗战争推高通胀风险",
          "url": "https://wallstreetcn.com/livenews/3069058",
          "source": "华尔街见闻-快讯",
          "ranks": [
            5,
            23
          ],
          "is_new": false,
          "appearance_count": 2,
          "time_info": "[00时52分 ~ 01时43分]"
        },
        {
          "title": "几个小时内“180度转变”！美国从“反对”到“力促”史上最大规模战略油储释放，背后是特朗普的忧虑",
          "url": "https://wallstreetcn.com/articles/3767287",
          "source": "华尔街见闻",
          "ranks": [
            6
          ],
          "is_new": false,
          "appearance_count": 3,
          "time_info": "[00时52分 ~ 02时42分]"
        },
        {
          "title": "美国防部被曝龙虾门",
          "url": "https://s.weibo.com/weibo?q=%23%E7%BE%8E%E5%9B%BD%E9%98%B2%E9%83%A8%E8%A2%AB%E6%9B%9D%E9%BE%99%E8%99%BE%E9%97%A8%23&t=31&band_rank=6&Refer=top",
          "source": "微博",
          "ranks": [
            6
          ],
          "is_new": false,
          "appearance_count": 3,
          "time_info": "[00时52分 ~ 02时42分]"
        },
        {
          "title": "伊朗伊斯兰革命卫队称袭击美国油轮",
          "url": "https://news.ifeng.com/c/8rR9ZmxHx0n",
          "source": "凤凰网",
          "ranks": [
            9
          ],
          "is_new": false,
          "appearance_count": 3,
          "time_info": "[00时52分 ~ 02时42分]"
        },
        {
          "title": "美能源部长：美国暂未准备好在霍尔木兹海峡为油轮护航",
          "url": "https://www.cls.cn/detail/2311322",
          "source": "财联社热门",
          "ranks": [
            13
          ],
          "is_new": false,
          "appearance_count": 3,
          "time_info": "[00时52分 ~ 02时42分]"
        },
        {
          "title": "伊朗袭击美国油轮 火光冲天",
          "url": "https://www.toutiao.com/trending/7616332350032514586/",
          "source": "今日头条",
          "ranks": [
            16
          ],
          "is_new": false,
          "appearance_count": 3,
          "time_info": "[00时52分 ~ 02时42分]"
        },
        {
          "title": "台湾花莲县发生5.3级地震",
          "url": "https://www.douyin.com/hot/2428622",
          "source": "抖音",
          "ranks": [
            17
          ],
          "is_new": false,
          "appearance_count": 3,
          "time_info": "[00时52分 ~ 02时42分]"
        },
        {
          "title": "美国将对 16 个贸易伙伴发起 301 调查，中国、欧盟、日本、印度、墨西哥等在内，会带来哪些影响？",
          "url": "https://www.zhihu.com/question/2015379875393976162",
          "source": "知乎",
          "ranks": [
            18
          ],
          "is_new": false,
          "appearance_count": 3,
          "time_info": "[00时52分 ~ 02时42分]"
        },
        {
          "title": "美国汽油价创21个月新高，零工群体在加油站感受切肤之痛",
          "url": "https://wallstreetcn.com/livenews/3069080",
          "source": "华尔街见闻-快讯",
          "ranks": [
            6,
            21
          ],
          "is_new": false,
          "appearance_count": 2,
          "time_info": "[01时43分 ~ 02时42分]"
        },
        {
          "title": "美国财政部拍卖220亿美元30年期国债，得标利率4.871%（2月12日为4.750%），投标倍数2.45（前次为2.66）。",
          "url": "https://wallstreetcn.com/livenews/3069079",
          "source": "华尔街见闻-快讯",
          "ranks": [
            7,
            22
          ],
          "is_new": false,
          "appearance_count": 2,
          "time_info": "[01时43分 ~ 02时42分]"
        },
        {
          "title": "美国参议院多数党领袖约翰·图恩（John Thune）：希望在下周选民身份立法的党派博弈结束后，推动参议院审议能源许可和加密货币法案。 参议员们正在制定一项市场结构法案，希望该法案能“很快”提交委员会通过。 参议院还可能着手改革能源和基础设施项目的许可规则。 计划下周将选民身份立法提交表决，但目前该法案尚无途径达到60票的通过门槛，也无法规避现有的议事规则。",
          "url": "https://wallstreetcn.com/livenews/3069054",
          "source": "华尔街见闻-快讯",
          "ranks": [
            8,
            26
          ],
          "is_new": false,
          "appearance_count": 2,
          "time_info": "[00时52分 ~ 01时43分]"
        },
        {
          "title": "PayPay美国IPO首日开盘报19美元，此前给出的IPO发行价为每股16美元。",
          "url": "https://wallstreetcn.com/livenews/3069071",
          "source": "华尔街见闻-快讯",
          "ranks": [
            14,
            29
          ],
          "is_new": false,
          "appearance_count": 2,
          "time_info": "[01时43分 ~ 02时42分]"
        },
        {
          "title": "伊朗称袭击美国油轮",
          "url": "https://search.bilibili.com/all?keyword=%E4%BC%8A%E6%9C%97%E7%A7%B0%E8%A2%AD%E5%87%BB%E7%BE%8E%E5%9B%BD%E6%B2%B9%E8%BD%AE",
          "source": "bilibili 热搜",
          "ranks": [
            29,
            30
          ],
          "is_new": false,
          "appearance_count": 2,
          "time_info": "[00时52分 ~ 01时43分]"
        },
        {
          "title": "市场消息：美国密歇根州犹太教堂枪击案嫌疑人已死亡。",
          "url": "https://flash.jin10.com/detail/20260313020454140800",
          "source": "金十数据",
          "ranks": [
            7
          ],
          "is_new": true,
          "appearance_count": 1,
          "time_info": "02时42分"
        },
        {
          "title": "伊朗革命卫队公共关系部：海军对位于米纳萨勒曼港的美国第五舰队恐怖分子总部发动毁灭性打击。",
          "url": "https://flash.jin10.com/detail/20260313004303367800",
          "source": "金十数据",
          "ranks": [
            8
          ],
          "is_new": false,
          "appearance_count": 1,
          "time_info": "00时52分"
        },
        {
          "title": "在腐败调查后，美国重新开放了位于圣多明各的缉毒署办事处。",
          "url": "https://flash.jin10.com/detail/20260313020102675800",
          "source": "金十数据",
          "ranks": [
            8
          ],
          "is_new": true,
          "appearance_count": 1,
          "time_info": "02时42分"
        },
        {
          "title": "美国财长贝森特将于3月15-16日前往法国。",
          "url": "https://wallstreetcn.com/livenews/3069097",
          "source": "华尔街见闻-快讯",
          "ranks": [
            8
          ],
          "is_new": true,
          "appearance_count": 1,
          "time_info": "02时42分"
        },
        {
          "title": "48%的美国人将高油价归咎于特朗普，这一比例高于其他任何因素。",
          "url": "https://flash.jin10.com/detail/20260313004045966800",
          "source": "金十数据",
          "ranks": [
            9
          ],
          "is_new": false,
          "appearance_count": 1,
          "time_info": "00时52分"
        },
        {
          "title": "美国能源部宣布19亿美元投资，用于升级电网、降低电力成本。",
          "url": "https://wallstreetcn.com/livenews/3069096",
          "source": "华尔街见闻-快讯",
          "ranks": [
            9
          ],
          "is_new": true,
          "appearance_count": 1,
          "time_info": "02时42分"
        },
        {
          "title": "据熟悉美西方情报的人士透露，俄罗斯目前正在向伊朗提供各种情报，包括卫星影像和无人机目标战术，以帮助伊朗反击该地区的美军。目前尚不确定俄罗斯向伊朗提供的情报有多有效、多及时，以及俄罗斯提供可操作信息的频率。",
          "url": "https://flash.jin10.com/detail/20260313015632390800",
          "source": "金十数据",
          "ranks": [
            10
          ],
          "is_new": true,
          "appearance_count": 1,
          "time_info": "02时42分"
        },
        {
          "title": "市场消息：美国参议员凯恩预计，有关伊朗女子学校遇袭事件的初步报告“很快”就会出炉，但不会是今天。",
          "url": "https://flash.jin10.com/detail/20260313003808477800",
          "source": "金十数据",
          "ranks": [
            11
          ],
          "is_new": false,
          "appearance_count": 1,
          "time_info": "00时52分"
        },
        {
          "title": "分析：美国战略石油储备最早5月中旬才能抵达亚洲紧缺地区",
          "url": "https://wallstreetcn.com/livenews/3069088",
          "source": "华尔街见闻-快讯",
          "ranks": [
            14
          ],
          "is_new": true,
          "appearance_count": 1,
          "time_info": "02时42分"
        },
        {
          "title": "美国财政部自11月以来首次削减6周期国库券发行规模",
          "url": "https://wallstreetcn.com/livenews/3069044",
          "source": "华尔街见闻-快讯",
          "ranks": [
            16
          ],
          "is_new": false,
          "appearance_count": 1,
          "time_info": "00时52分"
        },
        {
          "title": "美国纽约市长马姆达尼面临城市财政问题的新警报",
          "url": "https://wallstreetcn.com/livenews/3069069",
          "source": "华尔街见闻-快讯",
          "ranks": [
            16
          ],
          "is_new": false,
          "appearance_count": 1,
          "time_info": "01时43分"
        },
        {
          "title": "市场消息：美国参议院否决民主党提出的为运输安全管理局拨款的请求，僵局持续。",
          "url": "https://flash.jin10.com/detail/20260313010636403800",
          "source": "金十数据",
          "ranks": [
            17
          ],
          "is_new": false,
          "appearance_count": 1,
          "time_info": "01时43分"
        },
        {
          "title": "美国财政部拍卖四周期国债，得标利率3.640%，投标倍数2.77。 拍卖八周期国债，得标利率3.625%，投标倍数3.10。",
          "url": "https://wallstreetcn.com/livenews/3069041",
          "source": "华尔街见闻-快讯",
          "ranks": [
            17
          ],
          "is_new": false,
          "appearance_count": 1,
          "time_info": "00时52分"
        },
        {
          "title": "美国参议院少数党领袖舒默：唐纳德·特朗普怎么会没预见到霍尔木兹海峡危机呢？一个略懂地缘政治的大学生都能告诉你，伊朗最大的筹码就是这条狭窄的通道，世界上很大一部分石油都必须经过这里运输。而现在，美国政府正忙于控制事态发展，应对不断上涨的油价。",
          "url": "https://flash.jin10.com/detail/20260313010502775800",
          "source": "金十数据",
          "ranks": [
            19
          ],
          "is_new": false,
          "appearance_count": 1,
          "time_info": "01时43分"
        },
        {
          "title": "智利方面称，已与美国签署关于关键矿产和稀土的联合声明。",
          "url": "https://flash.jin10.com/detail/20260313014315200800",
          "source": "金十数据",
          "ranks": [
            19
          ],
          "is_new": true,
          "appearance_count": 1,
          "time_info": "02时42分"
        },
        {
          "title": "美国上诉法院驳回了阻止加州执行儿童在线隐私法的禁令，但表示该州无权执行该法的部分条款。",
          "url": "https://flash.jin10.com/detail/20260313002421118800",
          "source": "金十数据",
          "ranks": [
            20
          ],
          "is_new": false,
          "appearance_count": 1,
          "time_info": "00时52分"
        },
        {
          "title": "美国五角大楼代理主计长Jules Hurst：国防部正研究补充拨款请求选项。 2027财年预算请求将在不久之后提出。",
          "url": "https://wallstreetcn.com/livenews/3069037",
          "source": "华尔街见闻-快讯",
          "ranks": [
            20
          ],
          "is_new": false,
          "appearance_count": 1,
          "time_info": "00时52分"
        },
        {
          "title": "美国至3月12日30年期国债竞拍-投标倍数 2.45，前值2.66。",
          "url": "https://flash.jin10.com/detail/20260313010205683800",
          "source": "金十数据",
          "ranks": [
            21
          ],
          "is_new": false,
          "appearance_count": 1,
          "time_info": "01时43分"
        },
        {
          "title": "美国国务院发言人帕特尔：美国联邦调查局人员正与密歇根州的合作伙伴一道赶赴现场，应对密歇根州西布卢姆菲尔德犹太教堂外发生的疑似车辆冲撞和持枪扫射事件。",
          "url": "https://flash.jin10.com/detail/20260313013620102800",
          "source": "金十数据",
          "ranks": [
            21
          ],
          "is_new": true,
          "appearance_count": 1,
          "time_info": "02时42分"
        },
        {
          "title": "市场消息：美国《21世纪住房之路法案》在参议院以89票赞成、10票反对获得通过，这是一项旨在解决美国住房负担能力问题的法案，获得了两党的一致支持。",
          "url": "https://flash.jin10.com/detail/20260313002324812800",
          "source": "金十数据",
          "ranks": [
            22
          ],
          "is_new": false,
          "appearance_count": 1,
          "time_info": "00时52分"
        },
        {
          "title": "美国至3月12日30年期国债竞拍-得标利率配置百分比 59.56%，前值1.2%。",
          "url": "https://flash.jin10.com/detail/20260313010205682800",
          "source": "金十数据",
          "ranks": [
            22
          ],
          "is_new": false,
          "appearance_count": 1,
          "time_info": "01时43分"
        },
        {
          "title": "受中东局势紧张和油价逼近每桶100美元的提振，美国石油基金(USO)本月价格上涨超过40%，有望创下2018年以来的最高水平，周四收于116.60美元。",
          "url": "https://flash.jin10.com/detail/20260313013405950800",
          "source": "金十数据",
          "ranks": [
            22
          ],
          "is_new": true,
          "appearance_count": 1,
          "time_info": "02时42分"
        },
        {
          "title": "美国至3月12日30年期国债竞拍-得标利率 4.871%，前值4.75%。",
          "url": "https://flash.jin10.com/detail/20260313010205660800",
          "source": "金十数据",
          "ranks": [
            23
          ],
          "is_new": false,
          "appearance_count": 1,
          "time_info": "01时43分"
        },
        {
          "title": "市场消息：美国称在伊朗境内约6000个目标遭到袭击。",
          "url": "https://flash.jin10.com/detail/20260313010048650800",
          "source": "金十数据",
          "ranks": [
            25
          ],
          "is_new": false,
          "appearance_count": 1,
          "time_info": "01时43分"
        },
        {
          "title": "美国参议院投票通过住房可负担性法案，将其送交众议院。",
          "url": "https://flash.jin10.com/detail/20260313001903375800",
          "source": "金十数据",
          "ranks": [
            28
          ],
          "is_new": false,
          "appearance_count": 1,
          "time_info": "00时52分"
        },
        {
          "title": "乌克兰总统泽连斯基：是伊朗人率先向乌克兰发射了“沙赫德”无人机。当时并不存在俄罗斯操作人员，他们是接受相关训练的。",
          "url": "https://flash.jin10.com/detail/20260313005706559800",
          "source": "金十数据",
          "ranks": [
            28
          ],
          "is_new": false,
          "appearance_count": 1,
          "time_info": "01时43分"
        },
        {
          "title": "英国30年期国债收益率涨12个基点，报5.47%，创10月份以来新高。 美国原油期货涨幅扩大至10%，投资者关注通胀风险。",
          "url": "https://wallstreetcn.com/livenews/3069027",
          "source": "华尔街见闻-快讯",
          "ranks": [
            28
          ],
          "is_new": false,
          "appearance_count": 1,
          "time_info": "00时52分"
        },
        {
          "title": "根据“战争研究所”和“美国企业研究所”的数据，自伊朗战争开始以来，已有16艘民用船只（油轮、集装箱船和其他散货船）遭到袭击。",
          "url": "https://flash.jin10.com/detail/20260313001730933800",
          "source": "金十数据",
          "ranks": [
            29
          ],
          "is_new": false,
          "appearance_count": 1,
          "time_info": "00时52分"
        },
        {
          "title": "软银支持的日本数字钱包运营商PayPay登陆美股，开盘涨超13%。",
          "url": "https://flash.jin10.com/detail/20260313005601624800",
          "source": "金十数据",
          "ranks": [
            29
          ],
          "is_new": false,
          "appearance_count": 1,
          "time_info": "01时43分"
        },
        {
          "title": "市场消息：美国取暖油价格突破5美元/加仑。",
          "url": "https://flash.jin10.com/detail/20260313001118878800",
          "source": "金十数据",
          "ranks": [
            30
          ],
          "is_new": false,
          "appearance_count": 1,
          "time_info": "00时52分"
        },
        {
          "title": "GasBuddy报告称，目前美国已有8个州的柴油平均价格超过每加仑5美元，其中加州的柴油价格飙升至每加仑6.16美元。",
          "url": "https://flash.jin10.com/detail/20260313005417924800",
          "source": "金十数据",
          "ranks": [
            30
          ],
          "is_new": false,
          "appearance_count": 1,
          "time_info": "01时43分"
        }
      ]
    }
  ],
  "report_image_url": "https://wudongdefeng.github.io/TrendRadar/img/news.jpg"
}