{
  "generated_at": "2026-05-21T07:07:14.152708+08:00",
  "total_titles_processed": 555,
  "failed_sources": [],
  "trends": [
    {
      "keyword_group": "美国 大陆 日本 俄罗斯 台湾",
      "match_count": 47,
      "titles": [
        {
          "title": "习近平同俄罗斯总统普京会谈",
          "url": "https://search.bilibili.com/all?keyword=%E4%B9%A0%E8%BF%91%E5%B9%B3%E5%90%8C%E4%BF%84%E7%BD%97%E6%96%AF%E6%80%BB%E7%BB%9F%E6%99%AE%E4%BA%AC%E4%BC%9A%E8%B0%88",
          "source": "bilibili 热搜",
          "ranks": [
            1
          ],
          "is_new": false,
          "appearance_count": 5,
          "time_info": "[00时50分 ~ 07时07分]"
        },
        {
          "title": "俄罗斯总统普京结束访华",
          "url": "https://search.bilibili.com/all?keyword=%E4%BF%84%E7%BD%97%E6%96%AF%E6%80%BB%E7%BB%9F%E6%99%AE%E4%BA%AC%E7%BB%93%E6%9D%9F%E8%AE%BF%E5%8D%8E",
          "source": "bilibili 热搜",
          "ranks": [
            2
          ],
          "is_new": false,
          "appearance_count": 5,
          "time_info": "[00时50分 ~ 07时07分]"
        },
        {
          "title": "国台办发言人就台湾地区领导人“5·20”讲话表态：充斥谎言与欺骗、敌意与对抗",
          "url": "https://m.thepaper.cn/newsDetail_forward_33203544",
          "source": "澎湃新闻",
          "ranks": [
            5,
            2,
            1
          ],
          "is_new": false,
          "appearance_count": 5,
          "time_info": "[00时50分 ~ 07时07分]"
        },
        {
          "title": "敦促乌克兰给白俄“松绑”，美国打这个算盘",
          "url": "https://news.ifeng.com/c/8tHsC4wYsD3",
          "source": "凤凰网",
          "ranks": [
            4
          ],
          "is_new": false,
          "appearance_count": 5,
          "time_info": "[00时50分 ~ 07时07分]"
        },
        {
          "title": "折腾10年后终止合同，美国海岸警卫队新舰“一地鸡毛”",
          "url": "https://news.ifeng.com/c/8tI0QZFebLF",
          "source": "凤凰网",
          "ranks": [
            5
          ],
          "is_new": false,
          "appearance_count": 5,
          "time_info": "[00时50分 ~ 07时07分]"
        },
        {
          "title": "视频丨俄罗斯总统普京抵达北京开启访华行程",
          "url": "https://m.thepaper.cn/newsDetail_forward_33200995",
          "source": "澎湃新闻",
          "ranks": [
            1
          ],
          "is_new": false,
          "appearance_count": 1,
          "time_info": "00时50分"
        },
        {
          "title": "路透调查：三分之一的日本企业正在使用或考虑使用AI机器人。交通运输设备制造商引领日本AI机器人应用热潮。",
          "url": "https://flash.jin10.com/detail/20260521070434459800",
          "source": "金十数据",
          "ranks": [
            1
          ],
          "is_new": true,
          "appearance_count": 1,
          "time_info": "07时07分"
        },
        {
          "title": "美国已经向伊朗发送新文本。 伊朗正在审阅，尚未做出回应。（伊朗媒体Tasnim）",
          "url": "https://wallstreetcn.com/livenews/3106888",
          "source": "华尔街见闻-快讯",
          "ranks": [
            3
          ],
          "is_new": false,
          "appearance_count": 1,
          "time_info": "03时15分"
        },
        {
          "title": "乌克兰总统泽连斯基：已经在着手加强这一方向的防御，同时也在对白俄罗斯以及俄罗斯境内部分构成威胁的地区采取预防性措施。",
          "url": "https://flash.jin10.com/detail/20260521003325817800",
          "source": "金十数据",
          "ranks": [
            4
          ],
          "is_new": false,
          "appearance_count": 1,
          "time_info": "00时50分"
        },
        {
          "title": "乌克兰总统泽连斯基：。俄罗斯正从该方向考虑对乌克兰发动更多攻击的方案，针对北部地区以及切尔尼戈夫—基辅方向。",
          "url": "https://flash.jin10.com/detail/20260521003305509800",
          "source": "金十数据",
          "ranks": [
            5
          ],
          "is_new": false,
          "appearance_count": 1,
          "time_info": "00时50分"
        },
        {
          "title": "美国情报部门秘密进行针对古巴的“战争推演”",
          "url": "https://flash.jin10.com/detail/20260521065902588800",
          "source": "金十数据",
          "ranks": [
            5
          ],
          "is_new": true,
          "appearance_count": 1,
          "time_info": "07时07分"
        },
        {
          "title": "郑丽文：特朗普叫台湾不要再讲“台独”，民进党还装听不懂",
          "url": "https://news.ifeng.com/c/8tHcSaikz2t",
          "source": "凤凰网",
          "ranks": [
            9
          ],
          "is_new": false,
          "appearance_count": 5,
          "time_info": "[00时50分 ~ 07时07分]"
        },
        {
          "title": "7 家日本车企 2026 财年净利预计腰斩，日本造车业为何如此不景气？日产汽车落后于市场了吗？",
          "url": "https://www.zhihu.com/question/2040362002791588829",
          "source": "知乎",
          "ranks": [
            16,
            18,
            17,
            15
          ],
          "is_new": false,
          "appearance_count": 5,
          "time_info": "[00时50分 ~ 07时07分]"
        },
        {
          "title": "详讯丨习近平同俄罗斯总统普京共同会见记者",
          "url": "https://m.thepaper.cn/newsDetail_forward_33203841",
          "source": "澎湃新闻",
          "ranks": [
            18,
            17
          ],
          "is_new": false,
          "appearance_count": 5,
          "time_info": "[00时50分 ~ 07时07分]"
        },
        {
          "title": "伊朗：将在“强烈不信任美国”的情况下继续推进谈判",
          "url": "https://news.ifeng.com/c/8tHkNrUtZwa",
          "source": "凤凰网",
          "ranks": [
            7
          ],
          "is_new": false,
          "appearance_count": 3,
          "time_info": "[05时44分 ~ 07时07分]"
        },
        {
          "title": "美股七巨头收盘播报｜周三（5月20日），美国科技股七巨头（Magnificent 7）指数涨1.17%，报225.84点。 “超大”市值科技股指数涨涨2.27%，报450.52点。",
          "url": "https://wallstreetcn.com/livenews/3106945",
          "source": "华尔街见闻-快讯",
          "ranks": [
            7,
            28
          ],
          "is_new": false,
          "appearance_count": 2,
          "time_info": "[05时44分 ~ 07时07分]"
        },
        {
          "title": "台湾人疯狂批发霸王茶姬回家",
          "url": "https://s.weibo.com/weibo?q=%23%E5%8F%B0%E6%B9%BE%E4%BA%BA%E7%96%AF%E7%8B%82%E6%89%B9%E5%8F%91%E9%9C%B8%E7%8E%8B%E8%8C%B6%E5%A7%AC%E5%9B%9E%E5%AE%B6%23&t=31&band_rank=25&Refer=top",
          "source": "微博",
          "ranks": [
            25
          ],
          "is_new": false,
          "appearance_count": 2,
          "time_info": "[07时06分 ~ 07时07分]"
        },
        {
          "title": "乌克兰总统泽连斯基：今天就白俄罗斯-布良斯克地区的局势进行了详细讨论。",
          "url": "https://flash.jin10.com/detail/20260521003124378800",
          "source": "金十数据",
          "ranks": [
            6
          ],
          "is_new": false,
          "appearance_count": 1,
          "time_info": "00时50分"
        },
        {
          "title": "美国10年期国债收益率下降至4.565%，接近盘中低点。",
          "url": "https://flash.jin10.com/detail/20260521025951502800",
          "source": "金十数据",
          "ranks": [
            6
          ],
          "is_new": false,
          "appearance_count": 1,
          "time_info": "03时15分"
        },
        {
          "title": "美联储会议纪要：决策者们提到美国国债市场中的对冲基金风险。",
          "url": "https://wallstreetcn.com/livenews/3106885",
          "source": "华尔街见闻-快讯",
          "ranks": [
            6
          ],
          "is_new": false,
          "appearance_count": 1,
          "time_info": "03时15分"
        },
        {
          "title": "美联储会议纪要发布后，美国10年期国债收益率维持下跌大约8.3个基点的状态不变，目前持稳于日低4.5617%附近，暂报4.5835%。 两年期美债收益率维持6.7个基点的跌幅，暂报4.0508%。 现货黄金涨1.1%，持稳于4530美元一线。 标普500指数目前涨0.89%，道指涨557点、涨幅1.1%，纳指涨348点、涨幅1.3%。",
          "url": "https://wallstreetcn.com/livenews/3106884",
          "source": "华尔街见闻-快讯",
          "ranks": [
            7
          ],
          "is_new": false,
          "appearance_count": 1,
          "time_info": "03时15分"
        },
        {
          "title": "美国总统特朗普：就破冰船问题感谢芬兰。 短期内将形成55艘破冰船的（船队）规模。",
          "url": "https://wallstreetcn.com/livenews/3106849",
          "source": "华尔街见闻-快讯",
          "ranks": [
            8
          ],
          "is_new": false,
          "appearance_count": 1,
          "time_info": "00时50分"
        },
        {
          "title": "SpaceX申请美国IPO的要点总结",
          "url": "https://wallstreetcn.com/livenews/3106966",
          "source": "华尔街见闻-快讯",
          "ranks": [
            9
          ],
          "is_new": true,
          "appearance_count": 1,
          "time_info": "07时07分"
        },
        {
          "title": "美国起诉古巴革命领袖劳尔·卡斯特罗",
          "url": "https://wallstreetcn.com/livenews/3106843",
          "source": "华尔街见闻-快讯",
          "ranks": [
            14
          ],
          "is_new": false,
          "appearance_count": 1,
          "time_info": "00时50分"
        },
        {
          "title": "日本将围绕能源措施动用5000亿日元储备资金。（NHK）",
          "url": "https://wallstreetcn.com/livenews/3106961",
          "source": "华尔街见闻-快讯",
          "ranks": [
            14
          ],
          "is_new": true,
          "appearance_count": 1,
          "time_info": "07时07分"
        },
        {
          "title": "特朗普对美国的封锁措施表示称赞。",
          "url": "https://flash.jin10.com/detail/20260521002731140800",
          "source": "金十数据",
          "ranks": [
            15
          ],
          "is_new": false,
          "appearance_count": 1,
          "time_info": "00时50分"
        },
        {
          "title": "美国总统特朗普与以色列总理内塔尼亚胡周二就伊朗问题进行了气氛紧张的通话。（Axios）",
          "url": "https://wallstreetcn.com/livenews/3106875",
          "source": "华尔街见闻-快讯",
          "ranks": [
            15
          ],
          "is_new": false,
          "appearance_count": 1,
          "time_info": "03时15分"
        },
        {
          "title": "穆迪宣布完成对美国联邦政府评级的定期审查。",
          "url": "https://flash.jin10.com/detail/20260521050213849800",
          "source": "金十数据",
          "ranks": [
            18
          ],
          "is_new": false,
          "appearance_count": 1,
          "time_info": "05时44分"
        },
        {
          "title": "亚马逊创始人贝佐斯：美国税法是裙带资本主义，需要修正",
          "url": "https://wallstreetcn.com/livenews/3106838",
          "source": "华尔街见闻-快讯",
          "ranks": [
            19
          ],
          "is_new": false,
          "appearance_count": 1,
          "time_info": "00时50分"
        },
        {
          "title": "美联储称美国金融体系脆弱性仍“值得关注”",
          "url": "https://flash.jin10.com/detail/20260521024248944800",
          "source": "金十数据",
          "ranks": [
            20
          ],
          "is_new": false,
          "appearance_count": 1,
          "time_info": "03时15分"
        },
        {
          "title": "美国总统特朗普：在伊朗问题上，美国受到广泛尊重。 关于伊朗的唯一问题是，是我们彻底消灭他们，还是他们签署文件。",
          "url": "https://wallstreetcn.com/livenews/3106837",
          "source": "华尔街见闻-快讯",
          "ranks": [
            20
          ],
          "is_new": false,
          "appearance_count": 1,
          "time_info": "00时50分"
        },
        {
          "title": "伊朗外长前往美国参加联合国会议的筹备工作仍然在推进职中。（伊朗电视台）",
          "url": "https://wallstreetcn.com/livenews/3106870",
          "source": "华尔街见闻-快讯",
          "ranks": [
            20
          ],
          "is_new": false,
          "appearance_count": 1,
          "time_info": "03时15分"
        },
        {
          "title": "德文能源独占鳌头，美国政府40亿美元油气开采权拍卖创历史新高",
          "url": "https://wallstreetcn.com/livenews/3106955",
          "source": "华尔街见闻-快讯",
          "ranks": [
            20
          ],
          "is_new": true,
          "appearance_count": 1,
          "time_info": "07时07分"
        },
        {
          "title": "美国上周原油总库存创纪录暴跌1780万桶，出口创历史新高引发供应紧缺隐忧",
          "url": "https://wallstreetcn.com/livenews/3106836",
          "source": "华尔街见闻-快讯",
          "ranks": [
            21
          ],
          "is_new": false,
          "appearance_count": 1,
          "time_info": "00时50分"
        },
        {
          "title": "伊朗称将在“强烈不信任美国”的情况下继续推进谈判",
          "url": "https://wallstreetcn.com/livenews/3106869",
          "source": "华尔街见闻-快讯",
          "ranks": [
            21
          ],
          "is_new": false,
          "appearance_count": 1,
          "time_info": "03时15分"
        },
        {
          "title": "美国30年期国债收益率跌至5.1085%。",
          "url": "https://wallstreetcn.com/livenews/3106835",
          "source": "华尔街见闻-快讯",
          "ranks": [
            22
          ],
          "is_new": false,
          "appearance_count": 1,
          "time_info": "00时50分"
        },
        {
          "title": "俄罗斯央行申请立即执行针对欧洲清算银行的法院判决",
          "url": "https://wallstreetcn.com/livenews/3106866",
          "source": "华尔街见闻-快讯",
          "ranks": [
            23
          ],
          "is_new": false,
          "appearance_count": 1,
          "time_info": "03时15分"
        },
        {
          "title": "花旗集团CEO弗雷泽：美国、加拿大和巴西作为净石油出口国，更能应对高企的能源价格。",
          "url": "https://flash.jin10.com/detail/20260521023811540800",
          "source": "金十数据",
          "ranks": [
            24
          ],
          "is_new": false,
          "appearance_count": 1,
          "time_info": "03时15分"
        },
        {
          "title": "SpaceX IPO承销商包括高盛、摩根士丹利、美国银行证券、花旗、摩根大通证券。",
          "url": "https://flash.jin10.com/detail/20260521045646803800",
          "source": "金十数据",
          "ranks": [
            24
          ],
          "is_new": false,
          "appearance_count": 1,
          "time_info": "05时44分"
        },
        {
          "title": "美国财政部拍卖160亿美元20年期国债，得标利率5.122%（4月22日为4.883%），投标倍数2.55（前次为2.68）。",
          "url": "https://wallstreetcn.com/livenews/3106864",
          "source": "华尔街见闻-快讯",
          "ranks": [
            24
          ],
          "is_new": false,
          "appearance_count": 1,
          "time_info": "03时15分"
        },
        {
          "title": "美国财政部拍卖四个月期国债，得标利率3.590%，投标倍数3.34。",
          "url": "https://wallstreetcn.com/livenews/3106832",
          "source": "华尔街见闻-快讯",
          "ranks": [
            25
          ],
          "is_new": false,
          "appearance_count": 1,
          "time_info": "00时50分"
        },
        {
          "title": "SpaceX申请美国IPO，代码SPCX。 将有两类股票：A类股和B类股。 （首次公开发行股票前）马斯克投票权合计为85.1%，将控制“SpaceX需要股东批准的事项”。 向马斯克授予2亿股业绩挂钩B类股。 特斯拉持有（SpaceX）将近1900万股A类股。 签署收购Cursor的选择权协议。",
          "url": "https://wallstreetcn.com/livenews/3106924",
          "source": "华尔街见闻-快讯",
          "ranks": [
            25
          ],
          "is_new": false,
          "appearance_count": 1,
          "time_info": "05时44分"
        },
        {
          "title": "荷兰天然气期货跌5.8%，至49欧元下方，投资者紧盯美国与伊朗对话的动向。",
          "url": "https://wallstreetcn.com/livenews/3106829",
          "source": "华尔街见闻-快讯",
          "ranks": [
            28
          ],
          "is_new": false,
          "appearance_count": 1,
          "time_info": "00时50分"
        },
        {
          "title": "英国政府：英国外交部本周召见了俄罗斯大使。",
          "url": "https://flash.jin10.com/detail/20260521000320003800",
          "source": "金十数据",
          "ranks": [
            29
          ],
          "is_new": false,
          "appearance_count": 1,
          "time_info": "00时50分"
        },
        {
          "title": "中集集团：未曾收到美国司法部关于特定非冷藏运输集装箱的产量并操纵其价格的法律文件",
          "url": "https://wallstreetcn.com/livenews/3106828",
          "source": "华尔街见闻-快讯",
          "ranks": [
            29
          ],
          "is_new": false,
          "appearance_count": 1,
          "time_info": "00时50分"
        },
        {
          "title": "布伦特原油日内跌幅达7.0%，报103.44美元/桶；WTI原油日内跌幅达6.5%，报97.31美元/桶。 美国10年期国债收益率跌10个基点，至4.56%。 上期所原油期货夜盘跌幅扩大至6.11%，现报641元人民币/桶。 据Pool Report报道，美国总统特朗普声称，与伊朗的对话处于“最终阶段”。",
          "url": "https://wallstreetcn.com/livenews/3106827",
          "source": "华尔街见闻-快讯",
          "ranks": [
            30
          ],
          "is_new": false,
          "appearance_count": 1,
          "time_info": "00时50分"
        },
        {
          "title": "伊朗外交部发言人：美国必须对伊朗船只表现出良好意愿，结束其海盗行径。（伊朗国家电视台）",
          "url": "https://wallstreetcn.com/livenews/3106858",
          "source": "华尔街见闻-快讯",
          "ranks": [
            30
          ],
          "is_new": false,
          "appearance_count": 1,
          "time_info": "03时15分"
        }
      ]
    }
  ],
  "report_image_url": "https://wudongdefeng.github.io/TrendRadar/img/news.jpg"
}